rhythm/__init__.py
rhythm/__main__.py
rhythm/client.py
rhythm/config.py
rhythm/core.py
rhythm/decorators.py
rhythm/init.py
rhythm/models.py
rhythm/registry.py
rhythm/rhythm_core.pypy310-pp73-aarch64-linux-gnu.so
rhythm/worker.py
rhythm_py-0.1.2.dist-info/METADATA
rhythm_py-0.1.2.dist-info/WHEEL
rhythm_py-0.1.2.dist-info/RECORD
